elastensor/__init__.py
elastensor/_version.py
elastensor/deformations.py
elastensor/deformator.py
elastensor/parsers/__init__.py
elastensor/parsers/main.py
elastensor/parsers/vasp.py
elastensor/structure/__init__.py
elastensor/structure/base.py
elastensor/structure/elastic.py
elastensor/utils/__init__.py
elastensor/utils/generator.py
elastensor/utils/validate.py
elastensor-0.0.1.dist-info/LICENSE
elastensor-0.0.1.dist-info/METADATA
elastensor-0.0.1.dist-info/WHEEL
elastensor-0.0.1.dist-info/top_level.txt
elastensor-0.0.1.dist-info/RECORD
