Metadata-Version: 2.2
Name: elastensor
Version: 0.0.1
Summary: A package designed to assist with the creation of 3rd order elastic constants from DFT
Home-page: https://github.com/antelmor/ElasTensor
Author: Andres Tellez Mora
Author-email: Andres Mora <at00021@mix.wvu.edu>, Logan Lang <lllang@mix.wvu.edu>
License: MIT License
Project-URL: Repository, https://github.com/romerogroup/ElasTensor
Project-URL: Issues, https://github.com/romerogroup/ElasTensor/issues
Project-URL: Changelog, https://github.com/romerogroup/ElasTensor/CHANGELOG.md
Keywords: dft,elastic,tensors,vasp,python
Classifier: Programming Language :: Python :: 3
Requires-Python: >=3.8
License-File: LICENSE
Requires-Dist: python-dotenv
Requires-Dist: numpy
Requires-Dist: pymatgen
Requires-Dist: ase
Requires-Dist: spglib
Requires-Dist: variconfig
Provides-Extra: dev
Requires-Dist: sphinx; extra == "dev"
Requires-Dist: sphinx_rtd_theme; extra == "dev"
Requires-Dist: pytest; extra == "dev"
Requires-Dist: setuptools; extra == "dev"
Requires-Dist: setuptools_scm; extra == "dev"
